popidd_io/__init__.py
popidd_io/_anno.py
popidd_io/_image.py
popidd_io/_reader.py
popidd_io/_widget.py
popidd_io/_writer.py
popidd_io/napari.yaml
popidd_io/_tests/__init__.py
popidd_io/_tests/test_reader.py
popidd_io/_tests/test_widget.py
popidd_io-0.0.3.dist-info/LICENSE
popidd_io-0.0.3.dist-info/METADATA
popidd_io-0.0.3.dist-info/WHEEL
popidd_io-0.0.3.dist-info/entry_points.txt
popidd_io-0.0.3.dist-info/top_level.txt
popidd_io-0.0.3.dist-info/RECORD
