Metadata-Version: 2.2
Name: popidd-io
Version: 0.0.3
Summary: A simple plugin to read digital pathology images and annotations Made at the IPU (ICR/RMH).
Author: Ferran Cardoso Rodriguez
Author-email: ferran.cardoso@icr.ac.uk
License: 
Classifier: Development Status :: 2 - Pre-Alpha
Classifier: Framework :: napari
Classifier: Intended Audience :: Developers
Classifier: License :: OSI Approved :: GNU General Public License v3 (GPLv3)
Classifier: Operating System :: OS Independent
Classifier: Programming Language :: Python
Classifier: Programming Language :: Python :: 3
Classifier: Programming Language :: Python :: 3 :: Only
Classifier: Programming Language :: Python :: 3.10
Classifier: Programming Language :: Python :: 3.11
Classifier: Programming Language :: Python :: 3.12
Classifier: Topic :: Scientific/Engineering :: Image Processing
Requires-Python: >=3.10
License-File: LICENSE
Requires-Dist: magicgui
Requires-Dist: qtpy
Requires-Dist: scikit-image
Requires-Dist: napari
Requires-Dist: numpy
Requires-Dist: zarr<3
Requires-Dist: dask
Requires-Dist: pathlib
Requires-Dist: tifffile==2025.1.10
Requires-Dist: imagecodecs
Requires-Dist: geopandas
Requires-Dist: pyarrow
Provides-Extra: testing
Requires-Dist: tox; extra == "testing"
Requires-Dist: pytest; extra == "testing"
Requires-Dist: pytest-cov; extra == "testing"
Requires-Dist: pytest-qt; extra == "testing"
Requires-Dist: napari; extra == "testing"
Requires-Dist: pyqt5; extra == "testing"
Requires-Dist: pre-commit; extra == "testing"
